LICENSE.txt
MANIFEST.in
README.txt
VERSION.txt
cerebrate.py
requirements.txt
setup.py
cerebrate.egg-info/PKG-INFO
cerebrate.egg-info/SOURCES.txt
cerebrate.egg-info/dependency_links.txt
cerebrate.egg-info/entry_points.txt
cerebrate.egg-info/requires.txt
cerebrate.egg-info/top_level.txt
replaymanager/__init__.py
replaymanager/replaymanager.py
replaysearch/ReplaySearcher.py
replaysearch/__init__.py