Metadata-Version: 1.1
Name: cerebrate
Version: 0.0.11
Summary: Offline Replay Manager for StarCraft II
Home-page: https://github.com/frugs/cerebrate
Author: Hugo Wainwright
Author-email: wainwrighthugo@gmail.com
License: UNKNOWN
Download-URL: https://github.com/frugs/cerebrate/tarball/0.0.11
Platform: UNKNOWN
